portion/__init__.py
portion/api.py
portion/const.py
portion/dict.py
portion/func.py
portion/interval.py
portion/io.py
portion-2.5.0.dist-info/LICENSE.txt
portion-2.5.0.dist-info/METADATA
portion-2.5.0.dist-info/WHEEL
portion-2.5.0.dist-info/top_level.txt
portion-2.5.0.dist-info/zip-safe
portion-2.5.0.dist-info/RECORD
