Metadata-Version: 2.1
Name: portion
Version: 2.5.0
Summary: Python data structure and operations for intervals
Home-page: https://github.com/AlexandreDecan/portion
Author: Alexandre Decan
License: LGPLv3
Keywords: interval operation range math
Classifier: License :: OSI Approved :: GNU Lesser General Public License v3 (LGPLv3)
Classifier: Development Status :: 5 - Production/Stable
Classifier: Intended Audience :: Developers
Classifier: Intended Audience :: Education
Classifier: Intended Audience :: Information Technology
Classifier: Intended Audience :: Science/Research
Classifier: Topic :: Scientific/Engineering :: Mathematics
Classifier: Programming Language :: Python :: 3 :: Only
Classifier: Programming Language :: Python :: 3.8
Classifier: Programming Language :: Python :: 3.9
Classifier: Programming Language :: Python :: 3.10
Classifier: Programming Language :: Python :: 3.11
Classifier: Programming Language :: Python :: 3.12
Requires-Python: ~= 3.8
License-File: LICENSE.txt
Requires-Dist: sortedcontainers~=2.2
Provides-Extra: test
Requires-Dist: pytest~=7.0; extra == "test"
Requires-Dist: coverage~=6.0; extra == "test"
Requires-Dist: black>=21.8b; extra == "test"
